scrapling_fetch_mcp/__init__.py
scrapling_fetch_mcp/_fetcher.py
scrapling_fetch_mcp/_markdownify.py
scrapling_fetch_mcp/_scrapling.py
scrapling_fetch_mcp/mcp.py
iflow_mcp_cyberchitta_scrapling_fetch_mcp-0.2.0.dist-info/METADATA
iflow_mcp_cyberchitta_scrapling_fetch_mcp-0.2.0.dist-info/WHEEL
iflow_mcp_cyberchitta_scrapling_fetch_mcp-0.2.0.dist-info/entry_points.txt
iflow_mcp_cyberchitta_scrapling_fetch_mcp-0.2.0.dist-info/licenses/LICENSE
iflow_mcp_cyberchitta_scrapling_fetch_mcp-0.2.0.dist-info/RECORD
