Metadata-Version: 2.4
Name: iflow-mcp_cyberchitta_scrapling-fetch-mcp
Version: 0.2.0
Summary: Helps AI assistants access text content from bot-protected websites. MCP server that fetches HTML/markdown from sites with anti-automation measures using Scrapling.
Project-URL: Homepage, https://github.com/cyberchitta/scrapling-fetch-mcp
Project-URL: Bug Tracker, https://github.com/cyberchitta/scrapling-fetch-mcp/issues
Author-email: restlessronin <88921269+restlessronin@users.noreply.github.com>
License:                                  Apache License
License-File: LICENSE
Classifier: Operating System :: OS Independent
Classifier: Programming Language :: Python :: 3
Requires-Python: >=3.10
Requires-Dist: beautifulsoup4>=4.14.2
Requires-Dist: browserforge>=1.2.3
Requires-Dist: camoufox>=0.4.11
Requires-Dist: curl-cffi>=0.13.0
Requires-Dist: lxml>=6.0.2
Requires-Dist: markdownify>=1.2.0
Requires-Dist: mcp>=1.15.0
Requires-Dist: msgspec>=0.19.0
Requires-Dist: packaging<25.0,>=24.1
Requires-Dist: playwright>=1.55.0
Requires-Dist: scrapling>=0.3.6
